imgutils/__init__.py
imgutils/ascii/__init__.py
imgutils/ascii/drawing.py
imgutils/config/__init__.py
imgutils/config/meta.py
imgutils/data/__init__.py
imgutils/data/background.py
imgutils/data/blob.py
imgutils/data/decode.py
imgutils/data/encode.py
imgutils/data/image.py
imgutils/data/layer.py
imgutils/data/pad.py
imgutils/data/url.py
imgutils/detect/__init__.py
imgutils/detect/base.py
imgutils/detect/booru_yolo.py
imgutils/detect/censor.py
imgutils/detect/eye.py
imgutils/detect/face.py
imgutils/detect/halfbody.py
imgutils/detect/hand.py
imgutils/detect/head.py
imgutils/detect/nudenet.py
imgutils/detect/person.py
imgutils/detect/similarity.py
imgutils/detect/text.py
imgutils/detect/visual.py
imgutils/edge/__init__.py
imgutils/edge/_base.py
imgutils/edge/canny.py
imgutils/edge/lineart.py
imgutils/edge/lineart_anime.py
imgutils/generic/__init__.py
imgutils/generic/classify.py
imgutils/generic/classify_timm.py
imgutils/generic/clip.py
imgutils/generic/enhance.py
imgutils/generic/multilabel_timm.py
imgutils/generic/siglip.py
imgutils/generic/yolo.py
imgutils/generic/yoloseg.py
imgutils/metadata/__init__.py
imgutils/metadata/geninfo.py
imgutils/metadata/lsb/__init__.py
imgutils/metadata/lsb/read.py
imgutils/metadata/lsb/write.py
imgutils/metrics/__init__.py
imgutils/metrics/aesthetic.py
imgutils/metrics/ccip.py
imgutils/metrics/dbaesthetic.py
imgutils/metrics/laplacian.py
imgutils/metrics/lpips.py
imgutils/metrics/psnr_.py
imgutils/ocr/__init__.py
imgutils/ocr/detect.py
imgutils/ocr/entry.py
imgutils/ocr/recognize.py
imgutils/operate/__init__.py
imgutils/operate/align.py
imgutils/operate/censor_.py
imgutils/operate/emoji_censor.png
imgutils/operate/heart_censor.png
imgutils/operate/imgcensor.py
imgutils/operate/smile_censor.png
imgutils/operate/squeeze.py
imgutils/pose/__init__.py
imgutils/pose/dwpose.py
imgutils/pose/format.py
imgutils/pose/visual.py
imgutils/preprocess/__init__.py
imgutils/preprocess/base.py
imgutils/preprocess/pillow.py
dghs_imgutils-0.19.0.dist-info/LICENSE
dghs_imgutils-0.19.0.dist-info/METADATA
dghs_imgutils-0.19.0.dist-info/WHEEL
dghs_imgutils-0.19.0.dist-info/top_level.txt
dghs_imgutils-0.19.0.dist-info/RECORD
