Metadata-Version: 2.1
Name: dghs-imgutils
Version: 0.19.0
Summary: A convenient and user-friendly anime-style image data processing library that integrates various advanced anime-style image processing models.
Home-page: https://github.com/deepghs/imgutils
Author: narugo1992, 7eu7d7
Author-email: narugo1992@deepghs.org
License: MIT
Keywords: A convenient and user-friendly anime-style image data processing library that integrates various advanced anime-style image processing models.
Classifier: Development Status :: 5 - Production/Stable
Classifier: Intended Audience :: Developers
Classifier: Intended Audience :: Science/Research
Classifier: Intended Audience :: Information Technology
Classifier: License :: OSI Approved :: MIT License
Classifier: Programming Language :: Python
Classifier: Programming Language :: Python :: 3
Classifier: Programming Language :: Python :: 3 :: Only
Classifier: Programming Language :: Python :: 3.8
Classifier: Programming Language :: Python :: 3.9
Classifier: Programming Language :: Python :: 3.10
Classifier: Programming Language :: Python :: 3.11
Classifier: Programming Language :: Python :: 3.12
Classifier: Programming Language :: Python :: 3.13
Classifier: Operating System :: OS Independent
Classifier: Operating System :: POSIX
Classifier: Operating System :: Microsoft :: Windows
Classifier: Operating System :: MacOS
Classifier: Topic :: Scientific/Engineering
Classifier: Topic :: Scientific/Engineering :: Image Processing
Classifier: Topic :: Multimedia :: Graphics
Classifier: Topic :: Software Development :: Libraries
Classifier: Topic :: Software Development :: Libraries :: Python Modules
Classifier: Typing :: Typed
Classifier: Natural Language :: English
Requires-Python: >=3.8
License-File: LICENSE
Requires-Dist: hbutils >=0.9.0
Requires-Dist: pillow
Requires-Dist: numpy <2
Requires-Dist: scikit-learn
Requires-Dist: huggingface-hub
Requires-Dist: tqdm
Requires-Dist: opencv-contrib-python
Requires-Dist: pandas
Requires-Dist: scipy
Requires-Dist: emoji <2.12,>=2.5.0
Requires-Dist: pilmoji >=1.3.0
Requires-Dist: shapely !=2.0.7
Requires-Dist: pyclipper
Requires-Dist: deprecation >=2.0.0
Requires-Dist: hfutils >=0.9.0
Requires-Dist: filelock
Requires-Dist: bchlib !=2.0.0,!=2.0.1,!=2.1.0,!=2.1.1,!=2.1.2,>=1.0.0
Requires-Dist: piexif
Requires-Dist: pyrfc6266 >=1
Requires-Dist: urlobject >=2
Requires-Dist: tokenizers <0.21,>=0.20.0 ; python_version < "3.9"
Requires-Dist: tokenizers >=0.20.0 ; python_version >= "3.9"
Provides-Extra: demo
Requires-Dist: gradio >=4.44.0 ; extra == 'demo'
Provides-Extra: doc
Requires-Dist: Jinja2 ~=3.0.0 ; extra == 'doc'
Requires-Dist: sphinx >=3.2.0 ; extra == 'doc'
Requires-Dist: sphinx-rtd-theme >=0.4.3 ; extra == 'doc'
Requires-Dist: enum-tools ~=0.9.0 ; extra == 'doc'
Requires-Dist: sphinx-toolbox ; extra == 'doc'
Requires-Dist: plantumlcli >=0.0.2 ; extra == 'doc'
Requires-Dist: packaging ; extra == 'doc'
Requires-Dist: sphinx-multiversion >=0.2.4 ; extra == 'doc'
Requires-Dist: where ~=1.0.2 ; extra == 'doc'
Requires-Dist: easydict <2,>=1.7 ; extra == 'doc'
Requires-Dist: responses >=0.20.0 ; extra == 'doc'
Requires-Dist: matplotlib ; extra == 'doc'
Requires-Dist: natsort ; extra == 'doc'
Requires-Dist: nbsphinx >=0.8.8 ; extra == 'doc'
Requires-Dist: ipython >=7.16.3 ; extra == 'doc'
Requires-Dist: psutil >=5.8.0 ; extra == 'doc'
Requires-Dist: ipykernel >=6.15 ; extra == 'doc'
Requires-Dist: py-cpuinfo >=8.0.0 ; extra == 'doc'
Requires-Dist: click >=7.0.0 ; extra == 'doc'
Requires-Dist: pyarrow ; extra == 'doc'
Provides-Extra: gpu
Requires-Dist: onnxruntime-gpu ; extra == 'gpu'
Provides-Extra: model
Requires-Dist: torch ; extra == 'model'
Requires-Dist: safetensors ; extra == 'model'
Provides-Extra: test
Requires-Dist: coverage >=5 ; extra == 'test'
Requires-Dist: mock >=4.0.3 ; extra == 'test'
Requires-Dist: flake8 ~=3.5 ; extra == 'test'
Requires-Dist: testfixtures >=6.18.5 ; extra == 'test'
Requires-Dist: pytest ~=6.2.5 ; extra == 'test'
Requires-Dist: pytest-cov ~=3.0.0 ; extra == 'test'
Requires-Dist: pytest-mock ~=3.6.1 ; extra == 'test'
Requires-Dist: pytest-xdist >=1.34.0 ; extra == 'test'
Requires-Dist: pytest-rerunfailures ~=10.2 ; extra == 'test'
Requires-Dist: pytest-timeout ~=2.0.2 ; extra == 'test'
Requires-Dist: pytest-benchmark ~=3.4.0 ; extra == 'test'
Requires-Dist: easydict <2,>=1.7 ; extra == 'test'
Requires-Dist: testtools >=2 ; extra == 'test'
Requires-Dist: where >=1.0.2 ; extra == 'test'
Requires-Dist: pytest-image-diff <0.0.13,>=0.0.11 ; extra == 'test'
Requires-Dist: matplotlib ; extra == 'test'
Requires-Dist: natsort ; extra == 'test'
Requires-Dist: huggingface-hub <0.32 ; extra == 'test'
Provides-Extra: torchvision
Requires-Dist: torch ; extra == 'torchvision'
Requires-Dist: torchvision ; extra == 'torchvision'
Provides-Extra: transformers
Requires-Dist: transformers ; extra == 'transformers'
Requires-Dist: torch ; extra == 'transformers'
Requires-Dist: torchvision ; extra == 'transformers'
